README.md
setup.py
src/testgear_adapter_pytest/__init__.py
src/testgear_adapter_pytest/fixture_context.py
src/testgear_adapter_pytest/fixture_manager.py
src/testgear_adapter_pytest/fixture_storage.py
src/testgear_adapter_pytest/listener.py
src/testgear_adapter_pytest/plugin.py
src/testgear_adapter_pytest/utils.py
src/testgear_adapter_pytest.egg-info/PKG-INFO
src/testgear_adapter_pytest.egg-info/SOURCES.txt
src/testgear_adapter_pytest.egg-info/dependency_links.txt
src/testgear_adapter_pytest.egg-info/entry_points.txt
src/testgear_adapter_pytest.egg-info/requires.txt
src/testgear_adapter_pytest.egg-info/top_level.txt
src/testgear_adapter_pytest/models/__init__.py
src/testgear_adapter_pytest/models/fixture.py